MANIFEST.in
requirements.txt
setup.cfg
setup.py
uPnPClient.egg-info/PKG-INFO
uPnPClient.egg-info/SOURCES.txt
uPnPClient.egg-info/dependency_links.txt
uPnPClient.egg-info/not-zip-safe
uPnPClient.egg-info/requires.txt
uPnPClient.egg-info/top_level.txt
upnpclient/__init__.py
upnpclient/const.py
upnpclient/errors.py
upnpclient/marshal.py
upnpclient/soap.py
upnpclient/ssdp.py
upnpclient/upnp.py
upnpclient/util.py