Metadata-Version: 1.1
Name: uPnPClient
Version: 0.0.1
Summary: Python 2 and 3 library for accessing uPnP devices. Based on the
Home-page: https://github.com/flyte/upnpclient
Author: Ellis Percival
Author-email: upnpclient@failcode.co.uk
License: MIT
Keywords: upnp
Platform: UNKNOWN
Classifier: Programming Language :: Python
Classifier: Intended Audience :: Developers
Classifier: License :: OSI Approved :: MIT License
Classifier: Natural Language :: English
Classifier: Operating System :: OS Independent
Classifier: Topic :: Communications
Classifier: Topic :: Home Automation
Classifier: Topic :: System :: Networking
